kesslerav/__init__.py
kesslerav/constants.py
kesslerav/media_switch.py
kesslerav/url_parser.py
kesslerav/protocol2k/__init__.py
kesslerav/protocol2k/io.py
kesslerav/protocol2k/media_switch.py
kessler_av-0.9.0.dist-info/METADATA
kessler_av-0.9.0.dist-info/WHEEL
kessler_av-0.9.0.dist-info/licenses/LICENSE
kessler_av-0.9.0.dist-info/RECORD
