Metadata-Version: 2.1
Name: kessler-av
Version: 0.9.0
Summary: API for controlling a Kramer media switch using Protocol 2000
Project-URL: Homepage, https://github.com/krohrbaugh/kessler-av
Project-URL: Bug Tracker, https://github.com/krohrbaugh/kessler-av/issues
Author-email: Kevin Rohrbaugh <code@rhrbgh.com>
License-File: LICENSE
Keywords: hdmi,home assistant,home automation,kramer,video
Classifier: Development Status :: 4 - Beta
Classifier: Intended Audience :: Developers
Classifier: License :: OSI Approved :: MIT License
Classifier: Natural Language :: English
Classifier: Operating System :: OS Independent
Classifier: Programming Language :: Python :: 3
Classifier: Topic :: Home Automation
Classifier: Topic :: Multimedia :: Video
Classifier: Topic :: Software Development :: Libraries :: Python Modules
Requires-Python: >=3.11
